{
  "kanda": 1,
  "prasna": 3,
  "anuvaka": 13,
  "panchasat": 2,
  "phrases": [
    {
      "text": "यज्ञ्ꣳ शृणोतु देवः सविता",
      "start": 32.8,
      "end": 37.84
    },
    {
      "text": "हवं मे",
      "start": 37.84,
      "end": 39.84
    },
    {
      "text": "देवीरापो अपां नपाद्य ऊर्मिर्हविष्य",
      "start": 39.84,
      "end": 45.4
    },
    {
      "text": "इन्द्रियावान् मदिन्तमस्तं देवेभ्यो देवत्रा",
      "start": 45.4,
      "end": 50.56
    },
    {
      "text": "धत्त शुक्रꣳ शुक्रपेभ्यो येषां",
      "start": 50.56,
      "end": 55.32
    },
    {
      "text": "भागः स्थ स्वाहा कार्.षिरस्यपाऽपां",
      "start": 55.32,
      "end": 59.68
    },
    {
      "text": "मृद्ध्रꣳ समुद्रस्य वोऽक्षित्या उन्नये",
      "start": 59.68,
      "end": 64.96
    },
    {
      "text": "यमग्ने पृथ्सु मर्त्यमावो वाजेषु",
      "start": 64.96,
      "end": 68.48
    },
    {
      "text": "यं जुनाः",
      "start": 68.48,
      "end": 70.2
    },
    {
      "text": "स यन्ता शश्वतीरिषः",
      "start": 70.2,
      "end": 73.2
    }
  ],
  "total_phrases": 10
}