{
  "kanda": 1,
  "prasna": 3,
  "anuvaka": 14,
  "panchasat": 8,
  "phrases": [
    {
      "text": "पवस आ सुवोर्जमिषं च नः",
      "start": 288.32,
      "end": 292.4
    },
    {
      "text": "आरे बाधस्व दुच्छुनां",
      "start": 292.4,
      "end": 296.48
    },
    {
      "text": "अग्ने पवस्व स्वपा अस्मे",
      "start": 296.48,
      "end": 299.44
    },
    {
      "text": "वर्चः सुवीर्यं",
      "start": 299.44,
      "end": 302.2
    },
    {
      "text": "दधत्पोषꣳ रयिं मयि",
      "start": 302.2,
      "end": 305.48
    },
    {
      "text": "अग्ने पावक रोचिषा मन्द्रया",
      "start": 305.48,
      "end": 308.08
    },
    {
      "text": "देव जिह्वया",
      "start": 308.08,
      "end": 308.92
    },
    {
      "text": "आ देवान्. वक्षि यक्षि च",
      "start": 308.92,
      "end": 310.84
    },
    {
      "text": "स नः पावक दीदिवोऽग्ने",
      "start": 310.84,
      "end": 312.56
    },
    {
      "text": "देवाꣳ इहा वह",
      "start": 312.56,
      "end": 314.48
    },
    {
      "text": "उप यज्ञ्ꣳ हविश्च नः",
      "start": 314.48,
      "end": 317.8
    },
    {
      "text": "अग्निः शुचिव्रततमः शुचिर् विप्रः",
      "start": 317.8,
      "end": 321.48
    },
    {
      "text": "शुचिः ( ) कविः",
      "start": 321.48,
      "end": 323.08
    },
    {
      "text": "शुची रोचत आहुतः",
      "start": 323.08,
      "end": 325.16
    },
    {
      "text": "उदग्ने शुचयस्तव शुक्रा भ्राजन्त ईरते",
      "start": 325.16,
      "end": 327.92
    },
    {
      "text": "तव ज्योतीꣳष्यर्चयः",
      "start": 327.92,
      "end": 335.48
    },
    {
      "text": "(पुरुनिष्ठः-पुर्वणीक-भरा-ऽभि-वयोभिर्-य-आयूꣳषि -",
      "start": 335.48,
      "end": 342.2
    }
  ],
  "total_phrases": 17
}